neo_ls_svm/__init__.py
neo_ls_svm/_affine_feature_map.py
neo_ls_svm/_affine_normalizer.py
neo_ls_svm/_affine_separator.py
neo_ls_svm/_coherent_linear_quantile_regressor.py
neo_ls_svm/_feature_maps.py
neo_ls_svm/_neo_ls_svm.py
neo_ls_svm/_quantizer.py
neo_ls_svm/_typing.py
neo_ls_svm/_weighted_quantile.py
neo_ls_svm/py.typed
neo_ls_svm-0.3.0.dist-info/LICENSE
neo_ls_svm-0.3.0.dist-info/METADATA
neo_ls_svm-0.3.0.dist-info/WHEEL
neo_ls_svm-0.3.0.dist-info/RECORD
