Metadata-Version: 2.1
Name: neo-ls-svm
Version: 0.3.0
Summary: Neo LS-SVM
Home-page: https://github.com/lsorber/neo-ls-svm
Author: Laurent Sorber
Author-email: laurent.sorber@gmail.com
Requires-Python: >=3.10,<4.0
Classifier: Programming Language :: Python :: 3
Classifier: Programming Language :: Python :: 3.10
Classifier: Programming Language :: Python :: 3.11
Classifier: Programming Language :: Python :: 3.12
Requires-Dist: numba (>=0.56.4)
Requires-Dist: numpy (>=1.22.4)
Requires-Dist: scikit-learn (>=1.1.3)
Requires-Dist: scipy (>=1.7.3)
Project-URL: Repository, https://github.com/lsorber/neo-ls-svm
